nwapp/__init__.py
nwapp/main.py
nwapp/utils.py
nwapp/scripts/__init__.py
nwapp/scripts/classfiles.py
nwapp/scripts/cnt.py
nwapp/scripts/contract_process.py
nwapp/scripts/dbtest.py
nwapp/scripts/hello.py
nwapp/scripts/nw.py
nwapp-1.5.dist-info/METADATA
nwapp-1.5.dist-info/RECORD
nwapp-1.5.dist-info/WHEEL
nwapp-1.5.dist-info/entry_points.txt
nwapp-1.5.dist-info/top_level.txt
